roux/__init__.py
roux/global_imports.py
roux/run.py
roux/lib/__init__.py
roux/lib/df.py
roux/lib/dfs.py
roux/lib/dict.py
roux/lib/google.py
roux/lib/io.py
roux/lib/seq.py
roux/lib/set.py
roux/lib/str.py
roux/lib/sys.py
roux/lib/text.py
roux/query/__init__.py
roux/query/biomart.py
roux/query/ensembl.py
roux/stat/__init__.py
roux/stat/binary.py
roux/stat/classify.py
roux/stat/cluster.py
roux/stat/compare.py
roux/stat/corr.py
roux/stat/diff.py
roux/stat/enrich.py
roux/stat/fit.py
roux/stat/io.py
roux/stat/network.py
roux/stat/norm.py
roux/stat/paired.py
roux/stat/set.py
roux/stat/solve.py
roux/stat/transform.py
roux/stat/variance.py
roux/viz/__init__.py
roux/viz/annot.py
roux/viz/ax_.py
roux/viz/bar.py
roux/viz/colors.py
roux/viz/dist.py
roux/viz/figure.py
roux/viz/heatmap.py
roux/viz/image.py
roux/viz/io.py
roux/viz/line.py
roux/viz/scatter.py
roux/viz/sequence.py
roux/viz/sets.py
roux/workflow/__init__.py
roux/workflow/df.py
roux/workflow/function.py
roux/workflow/io.py
roux/workflow/knit.py
roux/workflow/monitor.py
roux/workflow/version.py
roux/workflow/workflow.py
tests/__init__.py
tests/test_examples.py
roux-0.0.6.dist-info/LICENSE
roux-0.0.6.dist-info/METADATA
roux-0.0.6.dist-info/WHEEL
roux-0.0.6.dist-info/entry_points.txt
roux-0.0.6.dist-info/top_level.txt
roux-0.0.6.dist-info/RECORD
