Metadata-Version: 2.1
Name: roux
Version: 0.0.6
Summary: helper functions
Home-page: http://github.com/rraadd88/roux
Author: rraadd88
Author-email: rohanadandage@gmail.com
License: General Public License v. 3
Classifier: Programming Language :: Python
Classifier: Programming Language :: Python :: 3
Classifier: Programming Language :: Python :: 3.7
Classifier: Programming Language :: Python :: 3.8
Classifier: Programming Language :: Python :: 3.9
Classifier: License :: OSI Approved :: MIT License
Classifier: Operating System :: OS Independent
Requires-Python: >=3.7, <4
License-File: LICENSE
Requires-Dist: biopython (>=1.71)
Requires-Dist: regex (>=2018.7.11)
Requires-Dist: pandas (>=0.25.3)
Requires-Dist: pyyaml (>=5.1)
Requires-Dist: numpy (>=1.17.3)
Requires-Dist: matplotlib (>=2.2)
Requires-Dist: requests (>=2.19.1)
Requires-Dist: scipy (>=1.1.0)
Requires-Dist: tqdm (>=4.38.0)
Requires-Dist: fastparquet
Requires-Dist: pandarallel
Requires-Dist: xlrd
Requires-Dist: openpyxl
Requires-Dist: argh
Requires-Dist: icecream
Requires-Dist: watermark
Provides-Extra: all
Requires-Dist: pygraphviz ; extra == 'all'
Requires-Dist: pyensembl ; extra == 'all'
Requires-Dist: seaborn (>=0.8) ; extra == 'all'
Requires-Dist: gitpython ; extra == 'all'
Requires-Dist: statsmodels ; extra == 'all'
Requires-Dist: networkx ; extra == 'all'
Requires-Dist: pybiomart ; extra == 'all'
Requires-Dist: snakemake ; extra == 'all'
Provides-Extra: dev
Requires-Dist: pytest ; extra == 'dev'
Requires-Dist: ipython ; extra == 'dev'
Requires-Dist: ipywidgets ; extra == 'dev'
Requires-Dist: jupyter ; extra == 'dev'
Requires-Dist: sphinx ; extra == 'dev'
Requires-Dist: recommonmark ; extra == 'dev'
Requires-Dist: black ; extra == 'dev'
Requires-Dist: coveralls (==3.*) ; extra == 'dev'
Requires-Dist: flake8 ; extra == 'dev'
Requires-Dist: isort ; extra == 'dev'
Requires-Dist: pytest-cov (==2.*) ; extra == 'dev'
Requires-Dist: testbook ; extra == 'dev'
Provides-Extra: query
Requires-Dist: pyensembl ; extra == 'query'
Requires-Dist: pybiomart ; extra == 'query'
Provides-Extra: stat
Requires-Dist: statsmodels ; extra == 'stat'
Requires-Dist: networkx ; extra == 'stat'
Provides-Extra: viz
Requires-Dist: seaborn (>=0.8) ; extra == 'viz'
Provides-Extra: workflow
Requires-Dist: snakemake ; extra == 'workflow'
Requires-Dist: gitpython ; extra == 'workflow'
Requires-Dist: networkx ; extra == 'workflow'
Requires-Dist: pygraphviz ; extra == 'workflow'
